{"cameraMode":{"drawMode":0,"name":"Shaded","section":"Shading Mode"},"sceneLighting":true,"audioPlay":false,"sceneViewState":{"showFog":true,"showMaterialUpdate":false,"showSkybox":true,"showFlares":true,"showImageEffects":true,"showParticleSystems":true},"in2DMode":false,"pivot":{"x":2.5830399990081789,"y":-1.3574328422546387,"z":1.0182745456695557},"rotation":{"x":0.2003181278705597,"y":-0.7898081541061401,"z":0.47493550181388857,"w":0.3325721025466919},"size":8.1314115524292,"orthographic":false}